digital_filter_tools.py
digital_filter_tools-0.4.1.dist-info/LICENSE
digital_filter_tools-0.4.1.dist-info/METADATA
digital_filter_tools-0.4.1.dist-info/WHEEL
digital_filter_tools-0.4.1.dist-info/top_level.txt
digital_filter_tools-0.4.1.dist-info/RECORD
