Metadata-Version: 2.1
Name: digital-filter-tools
Version: 0.4.1
Summary: An educational module about digital filters
Home-page: https://framagit.org/fsincere/digital-filter-tools
Author: Fabrice Sincère
Author-email: fabrice.sincere@ac-grenoble.fr
Maintainer: Fabrice Sincère
Maintainer-email: fabrice.sincere@ac-grenoble.fr
License: UNKNOWN
Platform: UNKNOWN
Classifier: Programming Language :: Python :: 3
Classifier: Intended Audience :: Education
Classifier: Intended Audience :: Science/Research
Classifier: Topic :: Scientific/Engineering :: Physics
Classifier: License :: OSI Approved :: GNU General Public License v3 (GPLv3)
Classifier: Operating System :: OS Independent
Classifier: Natural Language :: French
Requires-Python: >=3
License-File: LICENSE
Requires-Dist: numpy
Requires-Dist: matplotlib
Requires-Dist: ac-electricity
